stactools/threedep/__init__.py
stactools/threedep/commands.py
stactools/threedep/constants.py
stactools/threedep/metadata.py
stactools/threedep/stac.py
stactools/threedep/utils.py
stactools_threedep-0.2.0.dist-info/LICENSE
stactools_threedep-0.2.0.dist-info/METADATA
stactools_threedep-0.2.0.dist-info/WHEEL
stactools_threedep-0.2.0.dist-info/top_level.txt
stactools_threedep-0.2.0.dist-info/RECORD
