Metadata-Version: 2.1
Name: stactools-threedep
Version: 0.2.0
Summary: PROVIDE DESCRIPTION HERE
Home-page: https://github.com/stactools-threedeps/stactools-threedep
Author: stac-utils
Author-email: stac@radiant.earth
License: UNKNOWN
Project-URL: Documentation, https://stactools-threedep.readthedocs.io/en/latest/
Project-URL: Issues, https://github.com/stactools-threedeps/stactools-threedep/issues
Keywords: stactools,pystac,catalog,STAC
Platform: UNKNOWN
Classifier: Development Status :: 4 - Beta
Classifier: License :: OSI Approved :: Apache Software License
Classifier: Programming Language :: Python :: 3.6
Classifier: Programming Language :: Python :: 3.7
Classifier: Programming Language :: Python :: 3.8
Classifier: Programming Language :: Python :: 3.9
License-File: LICENSE
Requires-Dist: stactools (~=0.2.1a0)
Requires-Dist: boto3 (~=1.17)
